{
  "schema_version": 1,
  "milestone": "M0D",
  "matrix_revision": "m0d-2026-07-22-r1",
  "inventory_revision": "m0d-2026-07-22-r1",
  "reference_commit": "79fbfa0",
  "commit": "79fbfa00953f3c1f4f06a23ba1f442e8eb7136c6",
  "mode": "clean",
  "canonical_command": [
    "python3",
    "tests/run_verification.py",
    "{compiler}",
    "{vm}",
    "--report",
    "{report_dir}/verification-report.json"
  ],
  "matrix_definition": {
    "cells": [
      {
        "cell_id": "build.default",
        "family": "build",
        "environment": "default",
        "commands": [
          [
            "cmake",
            "-S",
            ".",
            "-B",
            "{default_build_dir}"
          ],
          [
            "cmake",
            "--build",
            "{default_build_dir}"
          ]
        ],
        "coverage": [
          "compile"
        ],
        "reachability": {
          "kind": "environment-wrapper",
          "name": "matrix.clean.default"
        }
      },
      {
        "cell_id": "build.sanitizers",
        "family": "build",
        "environment": "sanitizers",
        "commands": [
          [
            "cmake",
            "-S",
            ".",
            "-B",
            "{sanitizer_build_dir}",
            "-DCOMPILER_DESIGN_ENABLE_WARNINGS=ON",
            "-DCOMPILER_DESIGN_ENABLE_SANITIZERS=ON"
          ],
          [
            "cmake",
            "--build",
            "{sanitizer_build_dir}"
          ]
        ],
        "coverage": [
          "compile",
          "sanitizer-build"
        ],
        "reachability": {
          "kind": "environment-wrapper",
          "name": "ci.sanitizers.build"
        }
      },
      {
        "cell_id": "build.warnings",
        "family": "build",
        "environment": "warnings",
        "commands": [
          [
            "cmake",
            "-S",
            ".",
            "-B",
            "{warnings_build_dir}",
            "-DCOMPILER_DESIGN_ENABLE_WARNINGS=ON"
          ],
          [
            "cmake",
            "--build",
            "{warnings_build_dir}"
          ]
        ],
        "coverage": [
          "compile",
          "warning-build"
        ],
        "reachability": {
          "kind": "environment-wrapper",
          "name": "ci.verify.warning-build"
        }
      },
      {
        "cell_id": "canonical.verification",
        "family": "canonical-runner",
        "environment": "default",
        "commands": [
          [
            "python3",
            "tests/run_verification.py",
            "{compiler}",
            "{vm}",
            "--report",
            "{report_dir}/verification-report.json"
          ]
        ],
        "coverage": [
          "cpp-tests",
          "python-goldens",
          "artifact-tests",
          "rust-vm-tests",
          "cargo-test"
        ],
        "reachability": {
          "kind": "matrix-wrapper",
          "name": "tests/run_verification_matrix.py"
        }
      },
      {
        "cell_id": "tests.artifact",
        "family": "artifact-tests",
        "environment": "default",
        "commands": [
          [
            "python3",
            "tests/bytecode_artifact_tests.py",
            "{compiler}",
            "{vm}"
          ]
        ],
        "coverage": [
          "artifact-tests"
        ],
        "reachability": {
          "kind": "canonical",
          "name": "tests/run_verification.py",
          "runner": "artifact"
        },
        "duplicate_of": "canonical.verification"
      },
      {
        "cell_id": "tests.cargo",
        "family": "cargo-test",
        "environment": "default",
        "commands": [
          [
            "cargo",
            "test",
            "--manifest-path",
            "{vm}/Cargo.toml"
          ]
        ],
        "coverage": [
          "cargo-test"
        ],
        "reachability": {
          "kind": "canonical",
          "name": "tests/run_verification.py",
          "runner": "cargo_test"
        },
        "duplicate_of": "canonical.verification"
      },
      {
        "cell_id": "tests.ctest",
        "family": "cpp-tests",
        "environment": "default",
        "commands": [
          [
            "ctest",
            "--test-dir",
            "{default_build_dir}",
            "--output-on-failure"
          ]
        ],
        "coverage": [
          "cpp-tests"
        ],
        "reachability": {
          "kind": "canonical",
          "name": "tests/run_verification.py",
          "runner": "ctest"
        },
        "duplicate_of": "canonical.verification"
      },
      {
        "cell_id": "tests.golden",
        "family": "python-goldens",
        "environment": "default",
        "commands": [
          [
            "python3",
            "tests/run_golden_tests.py",
            "{compiler}"
          ]
        ],
        "coverage": [
          "python-goldens"
        ],
        "reachability": {
          "kind": "canonical",
          "name": "tests/run_verification.py",
          "runner": "golden"
        },
        "duplicate_of": "canonical.verification"
      },
      {
        "cell_id": "tests.rust_vm",
        "family": "rust-vm-tests",
        "environment": "default",
        "commands": [
          [
            "python3",
            "tests/run_rust_vm_tests.py",
            "{compiler}",
            "{vm}",
            "--goldens"
          ]
        ],
        "coverage": [
          "rust-vm-tests"
        ],
        "reachability": {
          "kind": "canonical",
          "name": "tests/run_verification.py",
          "runner": "rust_vm_artifact,rust_vm_golden,rust_vm_runtime_error"
        },
        "duplicate_of": "canonical.verification"
      },
      {
        "cell_id": "tests.sanitizer_ctest",
        "family": "cpp-tests",
        "environment": "sanitizers",
        "commands": [
          [
            "ctest",
            "--test-dir",
            "{sanitizer_build_dir}",
            "--output-on-failure"
          ]
        ],
        "coverage": [
          "cpp-tests",
          "sanitizer-build"
        ],
        "reachability": {
          "kind": "environment-wrapper",
          "name": "ci.sanitizers.ctest"
        }
      }
    ],
    "measurement_policies": {
      "compile_time": {
        "unit": "seconds",
        "statistic": "observed",
        "repetitions": 1,
        "tolerance_percent": 50.0,
        "enforcement": "informational",
        "definition": "Wall-clock CMake configure plus build time for each clean build environment."
      },
      "test_duration": {
        "unit": "seconds",
        "statistic": "observed",
        "repetitions": 1,
        "tolerance_percent": 50.0,
        "enforcement": "informational",
        "definition": "Wall-clock canonical verification plus sanitizer CTest time; duplicate projections count once."
      },
      "artifact_size": {
        "unit": "bytes",
        "statistic": "exact",
        "repetitions": 1,
        "tolerance_bytes": 0,
        "enforcement": "deterministic",
        "root": "tests/bytecode_artifacts",
        "pattern": "expected.cdbc",
        "definition": "Count, total bytes, and SHA-256 of the checked-in artifact corpus."
      },
      "runtime_workload": {
        "unit": "seconds",
        "statistic": "median",
        "repetitions": 3,
        "tolerance_percent": 50.0,
        "enforcement": "informational",
        "definition": "Rust VM wall-clock execution after one compiler emission, with exact stdout validation."
      }
    },
    "workloads": [
      {
        "workload_id": "arithmetic",
        "fixture": "tests/bytecode_artifacts/arithmetic",
        "sources": [
          "tests/bytecode_artifacts/arithmetic/input.cd"
        ],
        "expected_output": "tests/bytecode_artifacts/arithmetic/run.out"
      },
      {
        "workload_id": "collection_helpers",
        "fixture": "tests/bytecode_artifacts/collection_helpers",
        "sources": [
          "tests/bytecode_artifacts/collection_helpers/input.cd"
        ],
        "expected_output": "tests/bytecode_artifacts/collection_helpers/run.out"
      },
      {
        "workload_id": "maps",
        "fixture": "tests/bytecode_artifacts/maps",
        "sources": [
          "tests/bytecode_artifacts/maps/input.cd"
        ],
        "expected_output": "tests/bytecode_artifacts/maps/run.out"
      },
      {
        "workload_id": "native_stdlib_math",
        "fixture": "tests/bytecode_artifacts/native_stdlib_math",
        "sources": [
          "tests/bytecode_artifacts/native_stdlib_math/input.cd"
        ],
        "expected_output": "tests/bytecode_artifacts/native_stdlib_math/run.out"
      },
      {
        "workload_id": "unicode_strings",
        "fixture": "tests/bytecode_artifacts/unicode_strings",
        "sources": [
          "tests/bytecode_artifacts/unicode_strings/input.cd"
        ],
        "expected_output": "tests/bytecode_artifacts/unicode_strings/run.out"
      }
    ]
  },
  "environment": {
    "build_mode": "clean",
    "toolchain": {
      "cmake": "cmake version 3.28.3",
      "cxx": "c++ (Ubuntu 13.3.0-6ubuntu2~24.04.1) 13.3.0",
      "python": "Python 3.12.4",
      "cargo": "cargo 1.94.1 (29ea6fb6a 2026-03-24)",
      "rustc": "rustc 1.94.1 (e408947bf 2026-03-25)"
    },
    "host": {
      "system": "Linux",
      "release": "6.18.33.2-microsoft-standard-WSL2",
      "version": "#1 SMP PREEMPT_DYNAMIC Thu Jun 18 21:54:43 UTC 2026",
      "machine": "x86_64",
      "processor": "x86_64",
      "python_implementation": "CPython",
      "cpu_count": 32
    },
    "cmake_cache": {
      "default": {
        "CMAKE_BUILD_TYPE": "",
        "CMAKE_GENERATOR": "Unix Makefiles"
      },
      "warnings": {
        "CMAKE_BUILD_TYPE": "",
        "CMAKE_GENERATOR": "Unix Makefiles"
      },
      "sanitizers": {
        "CMAKE_BUILD_TYPE": "",
        "CMAKE_GENERATOR": "Unix Makefiles"
      }
    }
  },
  "cells": [
    {
      "cell_id": "build.default",
      "family": "build",
      "environment": "default",
      "status": "executed",
      "passed": true,
      "duration_seconds": 43.044987
    },
    {
      "cell_id": "build.sanitizers",
      "family": "build",
      "environment": "sanitizers",
      "status": "executed",
      "passed": true,
      "duration_seconds": 80.737753
    },
    {
      "cell_id": "build.warnings",
      "family": "build",
      "environment": "warnings",
      "status": "executed",
      "passed": true,
      "duration_seconds": 43.284275
    },
    {
      "cell_id": "canonical.verification",
      "family": "canonical-runner",
      "environment": "default",
      "status": "executed",
      "passed": true,
      "duration_seconds": 23.583521,
      "report_path": "build/matrix/verification-report.json"
    },
    {
      "cell_id": "tests.artifact",
      "family": "artifact-tests",
      "environment": "default",
      "status": "covered",
      "passed": true,
      "covered_by": "canonical.verification",
      "duplicate_of": "canonical.verification"
    },
    {
      "cell_id": "tests.cargo",
      "family": "cargo-test",
      "environment": "default",
      "status": "covered",
      "passed": true,
      "covered_by": "canonical.verification",
      "duplicate_of": "canonical.verification"
    },
    {
      "cell_id": "tests.ctest",
      "family": "cpp-tests",
      "environment": "default",
      "status": "covered",
      "passed": true,
      "covered_by": "canonical.verification",
      "duplicate_of": "canonical.verification"
    },
    {
      "cell_id": "tests.golden",
      "family": "python-goldens",
      "environment": "default",
      "status": "covered",
      "passed": true,
      "covered_by": "canonical.verification",
      "duplicate_of": "canonical.verification"
    },
    {
      "cell_id": "tests.rust_vm",
      "family": "rust-vm-tests",
      "environment": "default",
      "status": "covered",
      "passed": true,
      "covered_by": "canonical.verification",
      "duplicate_of": "canonical.verification"
    },
    {
      "cell_id": "tests.sanitizer_ctest",
      "family": "cpp-tests",
      "environment": "sanitizers",
      "status": "executed",
      "passed": true,
      "duration_seconds": 41.808018
    }
  ],
  "measurements": {
    "compile_time": {
      "unit": "seconds",
      "statistic": "observed",
      "repetitions": 1,
      "samples_seconds": {
        "build.default": 43.044987,
        "build.sanitizers": 80.737753,
        "build.warnings": 43.284275
      },
      "total_seconds": 167.067016
    },
    "test_duration": {
      "unit": "seconds",
      "statistic": "observed",
      "repetitions": 1,
      "samples_seconds": {
        "canonical_verification": 23.583521,
        "sanitizer_ctest": 41.808018
      },
      "total_seconds": 65.391539
    },
    "artifact_size": {
      "root": "tests/bytecode_artifacts",
      "pattern": "expected.cdbc",
      "file_count": 58,
      "total_bytes": 129946,
      "sha256": "75cd11741c6e4abc74cbb8df97411df1b976bfb4ea767b02282e07456f40a161",
      "files": [
        {
          "path": "tests/bytecode_artifacts/adt_pattern_matching/expected.cdbc",
          "bytes": 1117
        },
        {
          "path": "tests/bytecode_artifacts/arithmetic/expected.cdbc",
          "bytes": 622
        },
        {
          "path": "tests/bytecode_artifacts/array_any_all/expected.cdbc",
          "bytes": 1716
        },
        {
          "path": "tests/bytecode_artifacts/array_count/expected.cdbc",
          "bytes": 1722
        },
        {
          "path": "tests/bytecode_artifacts/array_filter/expected.cdbc",
          "bytes": 3847
        },
        {
          "path": "tests/bytecode_artifacts/array_filter_shadowing/expected.cdbc",
          "bytes": 1746
        },
        {
          "path": "tests/bytecode_artifacts/array_find/expected.cdbc",
          "bytes": 1717
        },
        {
          "path": "tests/bytecode_artifacts/array_find_index/expected.cdbc",
          "bytes": 1743
        },
        {
          "path": "tests/bytecode_artifacts/array_flat_map/expected.cdbc",
          "bytes": 1843
        },
        {
          "path": "tests/bytecode_artifacts/array_map/expected.cdbc",
          "bytes": 3038
        },
        {
          "path": "tests/bytecode_artifacts/array_reduce/expected.cdbc",
          "bytes": 5938
        },
        {
          "path": "tests/bytecode_artifacts/array_reduce_shadowing/expected.cdbc",
          "bytes": 2063
        },
        {
          "path": "tests/bytecode_artifacts/collection_helpers/expected.cdbc",
          "bytes": 1322
        },
        {
          "path": "tests/bytecode_artifacts/compound_assignment/expected.cdbc",
          "bytes": 724
        },
        {
          "path": "tests/bytecode_artifacts/control_flow/expected.cdbc",
          "bytes": 1170
        },
        {
          "path": "tests/bytecode_artifacts/field_compound_assignment/expected.cdbc",
          "bytes": 1006
        },
        {
          "path": "tests/bytecode_artifacts/for_in_loops/expected.cdbc",
          "bytes": 1705
        },
        {
          "path": "tests/bytecode_artifacts/for_loops/expected.cdbc",
          "bytes": 1205
        },
        {
          "path": "tests/bytecode_artifacts/functions_arrays/expected.cdbc",
          "bytes": 2740
        },
        {
          "path": "tests/bytecode_artifacts/generic_enums/expected.cdbc",
          "bytes": 7161
        },
        {
          "path": "tests/bytecode_artifacts/generic_explicit_type_arguments/expected.cdbc",
          "bytes": 4305
        },
        {
          "path": "tests/bytecode_artifacts/generic_functions/expected.cdbc",
          "bytes": 3298
        },
        {
          "path": "tests/bytecode_artifacts/generic_lambdas/expected.cdbc",
          "bytes": 2744
        },
        {
          "path": "tests/bytecode_artifacts/generic_methods/expected.cdbc",
          "bytes": 3562
        },
        {
          "path": "tests/bytecode_artifacts/import_basic/expected.cdbc",
          "bytes": 1097
        },
        {
          "path": "tests/bytecode_artifacts/index_compound_assignment/expected.cdbc",
          "bytes": 984
        },
        {
          "path": "tests/bytecode_artifacts/literal_patterns/expected.cdbc",
          "bytes": 11476
        },
        {
          "path": "tests/bytecode_artifacts/map_clear/expected.cdbc",
          "bytes": 1426
        },
        {
          "path": "tests/bytecode_artifacts/map_for_in/expected.cdbc",
          "bytes": 2379
        },
        {
          "path": "tests/bytecode_artifacts/map_keys_values/expected.cdbc",
          "bytes": 860
        },
        {
          "path": "tests/bytecode_artifacts/map_merge/expected.cdbc",
          "bytes": 1379
        },
        {
          "path": "tests/bytecode_artifacts/map_remove/expected.cdbc",
          "bytes": 1360
        },
        {
          "path": "tests/bytecode_artifacts/maps/expected.cdbc",
          "bytes": 1743
        },
        {
          "path": "tests/bytecode_artifacts/match_expression/expected.cdbc",
          "bytes": 1237
        },
        {
          "path": "tests/bytecode_artifacts/match_guards/expected.cdbc",
          "bytes": 1665
        },
        {
          "path": "tests/bytecode_artifacts/member_calls_arrays/expected.cdbc",
          "bytes": 789
        },
        {
          "path": "tests/bytecode_artifacts/member_calls_strings/expected.cdbc",
          "bytes": 940
        },
        {
          "path": "tests/bytecode_artifacts/module_exports/expected.cdbc",
          "bytes": 1689
        },
        {
          "path": "tests/bytecode_artifacts/multi_file_functions/expected.cdbc",
          "bytes": 1077
        },
        {
          "path": "tests/bytecode_artifacts/named_payload_fields/expected.cdbc",
          "bytes": 1592
        },
        {
          "path": "tests/bytecode_artifacts/named_struct_runtime_type_name/expected.cdbc",
          "bytes": 447
        },
        {
          "path": "tests/bytecode_artifacts/named_struct_types/expected.cdbc",
          "bytes": 984
        },
        {
          "path": "tests/bytecode_artifacts/namespace_imports/expected.cdbc",
          "bytes": 1114
        },
        {
          "path": "tests/bytecode_artifacts/native_stdlib_math/expected.cdbc",
          "bytes": 641
        },
        {
          "path": "tests/bytecode_artifacts/native_stdlib_push_pop/expected.cdbc",
          "bytes": 807
        },
        {
          "path": "tests/bytecode_artifacts/native_stdlib_strings/expected.cdbc",
          "bytes": 962
        },
        {
          "path": "tests/bytecode_artifacts/native_stdlib_typeof/expected.cdbc",
          "bytes": 964
        },
        {
          "path": "tests/bytecode_artifacts/nullable_enum_patterns/expected.cdbc",
          "bytes": 5811
        },
        {
          "path": "tests/bytecode_artifacts/or_patterns/expected.cdbc",
          "bytes": 7319
        },
        {
          "path": "tests/bytecode_artifacts/ranges/expected.cdbc",
          "bytes": 4939
        },
        {
          "path": "tests/bytecode_artifacts/record_patterns/expected.cdbc",
          "bytes": 6095
        },
        {
          "path": "tests/bytecode_artifacts/runtime_diagnostics/expected.cdbc",
          "bytes": 826
        },
        {
          "path": "tests/bytecode_artifacts/struct_field_assignment/expected.cdbc",
          "bytes": 862
        },
        {
          "path": "tests/bytecode_artifacts/struct_method_compound_assignment/expected.cdbc",
          "bytes": 1842
        },
        {
          "path": "tests/bytecode_artifacts/struct_methods_basic/expected.cdbc",
          "bytes": 1345
        },
        {
          "path": "tests/bytecode_artifacts/struct_methods_mutation/expected.cdbc",
          "bytes": 1653
        },
        {
          "path": "tests/bytecode_artifacts/structs/expected.cdbc",
          "bytes": 1360
        },
        {
          "path": "tests/bytecode_artifacts/unicode_strings/expected.cdbc",
          "bytes": 2228
        }
      ]
    },
    "runtime_workload": {
      "unit": "seconds",
      "statistic": "median",
      "repetitions": 3,
      "samples_seconds": {
        "arithmetic": [
          0.016348,
          0.015558,
          0.015689
        ],
        "collection_helpers": [
          0.014942,
          0.01564,
          0.015072
        ],
        "maps": [
          0.015801,
          0.015695,
          0.016802
        ],
        "native_stdlib_math": [
          0.015641,
          0.016063,
          0.015627
        ],
        "unicode_strings": [
          0.016135,
          0.016095,
          0.01559
        ]
      },
      "median_seconds": {
        "arithmetic": 0.015689,
        "collection_helpers": 0.015072,
        "maps": 0.015801,
        "native_stdlib_math": 0.015641,
        "unicode_strings": 0.016095
      }
    }
  },
  "canonical_observation": {
    "inventory_revision": "m0d-2026-07-22-r1",
    "total": 1659,
    "passed": 1659,
    "failed": 0,
    "untracked_results": 0,
    "runners": [
      "artifact",
      "boundary_tokens",
      "cargo_test",
      "ctest",
      "golden",
      "golden_selftest",
      "malformed",
      "rust_vm_artifact",
      "rust_vm_golden",
      "rust_vm_runtime_error"
    ]
  },
  "runtime_workloads": [
    {
      "workload_id": "arithmetic",
      "fixture": "tests/bytecode_artifacts/arithmetic",
      "expected_output": "tests/bytecode_artifacts/arithmetic/run.out",
      "expected_output_sha256": "31b7dffb75ce583240142c52ed4cbe9e06b9ef7b15bc03a0ddcd6ed53e51c6ff",
      "repetitions": 3,
      "passed": true,
      "samples_seconds": [
        0.016348,
        0.015558,
        0.015689
      ],
      "median_seconds": 0.015689
    },
    {
      "workload_id": "collection_helpers",
      "fixture": "tests/bytecode_artifacts/collection_helpers",
      "expected_output": "tests/bytecode_artifacts/collection_helpers/run.out",
      "expected_output_sha256": "dcc24f4918770b0e7cdec8f74e93b33d5eb40823f5b95c8ca0175b07e9495cf6",
      "repetitions": 3,
      "passed": true,
      "samples_seconds": [
        0.014942,
        0.01564,
        0.015072
      ],
      "median_seconds": 0.015072
    },
    {
      "workload_id": "maps",
      "fixture": "tests/bytecode_artifacts/maps",
      "expected_output": "tests/bytecode_artifacts/maps/run.out",
      "expected_output_sha256": "0d2c158bc7f2eff56e9797a8d3ecdceb38ce306b194806281982389bb5a97754",
      "repetitions": 3,
      "passed": true,
      "samples_seconds": [
        0.015801,
        0.015695,
        0.016802
      ],
      "median_seconds": 0.015801
    },
    {
      "workload_id": "native_stdlib_math",
      "fixture": "tests/bytecode_artifacts/native_stdlib_math",
      "expected_output": "tests/bytecode_artifacts/native_stdlib_math/run.out",
      "expected_output_sha256": "1dd55023352e5b9cf58dda45c5ac13a4f61e465a448ed27804b4b177bcb5bee4",
      "repetitions": 3,
      "passed": true,
      "samples_seconds": [
        0.015641,
        0.016063,
        0.015627
      ],
      "median_seconds": 0.015641
    },
    {
      "workload_id": "unicode_strings",
      "fixture": "tests/bytecode_artifacts/unicode_strings",
      "expected_output": "tests/bytecode_artifacts/unicode_strings/run.out",
      "expected_output_sha256": "f88c44f65a4024ec193e1a5f40b5e1bac14696d0e134ae1fe9787a075374cb58",
      "repetitions": 3,
      "passed": true,
      "samples_seconds": [
        0.016135,
        0.016095,
        0.01559
      ],
      "median_seconds": 0.016095
    }
  ],
  "summary": {
    "total_cells": 10,
    "passed_cells": 10,
    "failed_cells": 0,
    "executed_cells": 5,
    "covered_cells": 5,
    "delegated_cells": 0,
    "reused_cells": 0,
    "total_workloads": 5,
    "passed_workloads": 5,
    "failed_workloads": 0
  },
  "errors": [],
  "comparison": {
    "passed": true,
    "deterministic_differences": [],
    "performance": [],
    "disposition": "baseline not requested"
  }
}
